[
  {
    "id": 1777388580648,
    "t": "Человек-бензопила",
    "series": "Человек-бензопила",
    "a": [
      "Тацуки Фудзимото"
    ],
    "v": 6,
    "p": 192,
    "y": "2022",
    "isbn": "9785389216747",
    "c": "https://i.postimg.cc/sxHRfHDL/006.jpg",
    "pub": "Азбука",
    "g": [
      "Сёнен",
      "Экшен",
      "Фэнтези"
    ],
    "tv": 0,
    "oneshot": false
  },
  {
    "id": 1777388604032,
    "t": "Человек-бензопила",
    "series": "Человек-бензопила",
    "a": [
      "Тацуки Фудзимото"
    ],
    "v": 12,
    "p": 184,
    "y": "2024",
    "isbn": "9785389259294",
    "c": "https://i.postimg.cc/X7h0TPP0/012.jpg",
    "pub": "Азбука",
    "g": [
      "Сёнен",
      "Экшен",
      "Фэнтези"
    ],
    "tv": 0,
    "oneshot": false
  },
  {
    "id": 1777398517477,
    "t": "Человек-бензопила",
    "series": "Человек-бензопила",
    "a": [
      "Тацуки Фудзимото"
    ],
    "v": 11,
    "p": 184,
    "y": "2024",
    "isbn": "9785389254008",
    "c": "https://i.postimg.cc/L6hpQSxm/011.jpg",
    "pub": "Азбука",
    "g": [
      "Сёнен",
      "Экшен",
      "Фэнтези"
    ],
    "tv": 0,
    "oneshot": false
  },
  {
    "id": 1777644246887,
    "t": "Человек-бензопила",
    "series": "Человек-бензопила",
    "a": [
      "Тацуки Фудзимото"
    ],
    "v": 1,
    "p": 384,
    "y": "2021",
    "isbn": "9785389202054",
    "c": "https://i.postimg.cc/zvGrrY50/001.jpg",
    "pub": "Азбука",
    "g": [
      "Сёнен",
      "Экшен",
      "Фэнтези"
    ],
    "tv": 0,
    "oneshot": false
  },
  {
    "id": 1777759717978,
    "t": "Человек-бензопила",
    "series": "Человек-бензопила",
    "a": [
      "Тацуки Фудзимото"
    ],
    "v": 7,
    "p": 192,
    "y": "2023",
    "isbn": "9785389227163",
    "c": "https://i.postimg.cc/h42n0vb9/007.jpg",
    "pub": "Азбука",
    "g": [
      "Сёнен",
      "Экшен",
      "Фэнтези"
    ],
    "tv": 0,
    "oneshot": false
  },
  {
    "id": 1777803882527,
    "t": "Человек-бензопила",
    "series": "Человек-бензопила",
    "a": [
      "Тацуки Фудзимото"
    ],
    "v": 13,
    "p": 184,
    "y": "2025",
    "isbn": "9785389272408",
    "c": "https://i.postimg.cc/3J6HPqqT/013.jpg",
    "pub": "Азбука",
    "g": [
      "Сёнен",
      "Экшен",
      "Фэнтези"
    ],
    "tv": 0,
    "oneshot": false
  },
  {
    "id": 1777826034932,
    "t": "Человек-бензопила",
    "series": "Человек-бензопила",
    "a": [
      "Тацуки Фудзимото"
    ],
    "v": 9,
    "p": 184,
    "y": "2023",
    "isbn": "9785389236509",
    "c": "https://i.postimg.cc/ryfT9sCb/009.jpg",
    "pub": "Азбука",
    "g": [
      "Сёнен",
      "Экшен",
      "Фэнтези"
    ],
    "tv": 0,
    "oneshot": false
  },
  {
    "id": 1777926736645,
    "t": "Человек-бензопила",
    "series": "Человек-бензопила",
    "a": [
      "Тацуки Фудзимото"
    ],
    "v": 2,
    "p": 384,
    "y": "2021",
    "isbn": "9785389203921",
    "c": "https://i.postimg.cc/RhZBBx97/002.jpg",
    "pub": "Азбука",
    "g": [
      "Сёнен",
      "Экшен",
      "Фэнтези"
    ],
    "tv": 0,
    "oneshot": false
  },
  {
    "id": 1777926831203,
    "t": "Человек-бензопила",
    "series": "Человек-бензопила",
    "a": [
      "Тацуки Фудзимото"
    ],
    "v": 3,
    "p": 392,
    "y": "2022",
    "isbn": "9785389207394",
    "c": "https://i.postimg.cc/4yxggRZz/003.jpg",
    "pub": "Азбука",
    "g": [
      "Сёнен",
      "Экшен",
      "Фэнтези"
    ],
    "tv": 0,
    "oneshot": false
  },
  {
    "id": 1777926981732,
    "t": "Человек-бензопила",
    "series": "Человек-бензопила",
    "a": [
      "Тацуки Фудзимото"
    ],
    "v": 4,
    "p": 392,
    "y": "2022",
    "isbn": "9785389210806",
    "c": "https://i.postimg.cc/x8122VY3/004.jpg",
    "pub": "Азбука",
    "g": [
      "Сёнен",
      "Экшен",
      "Фэнтези"
    ],
    "tv": 0,
    "oneshot": false
  },
  {
    "id": 1777927071114,
    "t": "Человек-бензопила",
    "series": "Человек-бензопила",
    "a": [
      "Тацуки Фудзимото"
    ],
    "v": 5,
    "p": 384,
    "y": "2022",
    "isbn": "9785389214309",
    "c": "https://i.postimg.cc/D0pKfpyC/005.jpg",
    "pub": "Азбука",
    "g": [
      "Сёнен",
      "Экшен",
      "Фэнтези"
    ],
    "tv": 0,
    "oneshot": false
  },
  {
    "id": 1777927328380,
    "t": "Человек-бензопила",
    "series": "Человек-бензопила",
    "a": [
      "Тацуки Фудзимото"
    ],
    "v": 8,
    "p": 184,
    "y": "2023",
    "isbn": "9785389230170",
    "c": "https://i.postimg.cc/Wp5V7z6G/008.jpg",
    "pub": "Азбука",
    "g": [
      "Сёнен",
      "Экшен",
      "Фэнтези"
    ],
    "tv": 0,
    "oneshot": false
  },
  {
    "id": 1777927525486,
    "t": "Человек-бензопила",
    "series": "Человек-бензопила",
    "a": [
      "Тацуки Фудзимото"
    ],
    "v": 10,
    "p": 200,
    "y": "2024",
    "isbn": "9785389246621",
    "c": "https://i.postimg.cc/ZK0SsmVQ/010.jpg",
    "pub": "Азбука",
    "g": [
      "Сёнен",
      "Экшен",
      "Фэнтези"
    ],
    "tv": 0,
    "oneshot": false
  },
  {
    "id": 1777927718719,
    "t": "Человек-бензопила",
    "series": "Человек-бензопила",
    "a": [
      "Тацуки Фудзимото"
    ],
    "v": 14,
    "p": 184,
    "y": "2025",
    "isbn": "9785389289789",
    "c": "https://i.postimg.cc/PrckB77q/014.jpg",
    "pub": "Азбука",
    "g": [
      "Сёнен",
      "Экшен",
      "Фэнтези"
    ],
    "tv": 0,
    "oneshot": false
  },
  {
    "id": 1777927800246,
    "t": "Человек-бензопила",
    "series": "Человек-бензопила",
    "a": [
      "Тацуки Фудзимото"
    ],
    "v": 15,
    "p": 192,
    "y": "2025",
    "isbn": "9785389303867",
    "c": "https://i.postimg.cc/fTFh6PPV/015.jpg",
    "pub": "Азбука",
    "g": [
      "Сёнен",
      "Экшен",
      "Фэнтези"
    ],
    "tv": 0,
    "oneshot": false
  },
  {
    "id": 1777996302576,
    "t": "Человек-бензопила",
    "series": "Человек-бензопила",
    "a": [
      "Тацуки Фудзимото"
    ],
    "v": 16,
    "p": 192,
    "y": "2025",
    "isbn": "9785389309661",
    "c": "https://i.postimg.cc/WbKPQyyw/016.jpg",
    "pub": "Азбука",
    "g": [
      "Сёнен",
      "Экшен",
      "Фэнтези"
    ],
    "tv": 0,
    "oneshot": false
  },
  {
    "id": 1777399873449,
    "t": "Токийские мстители",
    "series": "Токийские мстители",
    "a": [
      "Кэн Вакуи"
    ],
    "v": 1,
    "p": 394,
    "y": "2022",
    "isbn": "9785919964018",
    "c": "https://i.postimg.cc/SskL78wT/001.jpg",
    "pub": "XL Media",
    "g": [
      "Сёнен",
      "Экшен"
    ],
    "tv": 0,
    "oneshot": false
  },
  {
    "id": 1777400292637,
    "t": "Токийские мстители",
    "series": "Токийские мстители",
    "a": [
      "Кэн Вакуи"
    ],
    "v": 3,
    "p": 396,
    "y": "2022",
    "isbn": "9785919964209",
    "c": "https://i.postimg.cc/y8R0MvB8/003.jpg",
    "pub": "XL Media",
    "g": [
      "Сёнен",
      "Экшен"
    ],
    "tv": 0,
    "oneshot": false
  },
  {
    "id": 1778012428715,
    "t": "Токийские мстители",
    "series": "Токийские мстители",
    "a": [
      "Кэн Вакуи"
    ],
    "v": 2,
    "p": 394,
    "y": "2022",
    "isbn": "9785919964193",
    "c": "https://i.postimg.cc/52z8hn1t/002.jpg",
    "pub": "XL Media",
    "g": [
      "Сёнен",
      "Экшен"
    ],
    "tv": 0,
    "oneshot": false
  },
  {
    "id": 1778050640420,
    "t": "Токийские мстители",
    "series": "Токийские мстители",
    "a": [
      "Кэн Вакуи"
    ],
    "v": 4,
    "p": 402,
    "y": "2022",
    "isbn": "9785919964254",
    "c": "https://i.postimg.cc/j5dZwCBP/004.jpg",
    "pub": "XL Media",
    "g": [
      "Сёнен",
      "Экшен"
    ],
    "tv": 0,
    "oneshot": false
  },
  {
    "id": 1778050709696,
    "t": "Токийские мстители",
    "series": "Токийские мстители",
    "a": [
      "Кэн Вакуи"
    ],
    "v": 5,
    "p": 386,
    "y": "2023",
    "isbn": "9785919964322",
    "c": "https://i.postimg.cc/fLTBtk1Y/005.jpg",
    "pub": "XL Media",
    "g": [
      "Сёнен",
      "Экшен"
    ],
    "tv": 0,
    "oneshot": false
  },
  {
    "id": 1778051888845,
    "t": "Токийские мстители",
    "series": "Токийские мстители",
    "a": [
      "Кэн Вакуи"
    ],
    "v": 6,
    "p": 402,
    "y": "2023",
    "isbn": "9785919964346",
    "c": "https://i.postimg.cc/SsND2jHX/006.jpg",
    "pub": "XL Media",
    "g": [
      "Сёнен",
      "Экшен"
    ],
    "tv": 0,
    "oneshot": false
  },
  {
    "id": 1778054059009,
    "t": "Токийские мстители",
    "series": "Токийские мстители",
    "a": [
      "Кэн Вакуи"
    ],
    "v": 7,
    "p": 386,
    "y": "2023",
    "isbn": "9785919964438",
    "c": "https://i.postimg.cc/HxsBcjF7/007.webp",
    "pub": "XL Media",
    "g": [
      "Сёнен",
      "Экшен"
    ],
    "tv": 0,
    "oneshot": false
  },
  {
    "id": 1778054355050,
    "t": "Токийские мстители",
    "series": "Токийские мстители",
    "a": [
      "Кэн Вакуи"
    ],
    "v": 8,
    "p": 386,
    "y": "2023",
    "isbn": "9785919964452",
    "c": "https://i.postimg.cc/vBqXWbdL/008.webp",
    "pub": "XL Media",
    "g": [
      "Сёнен",
      "Экшен"
    ],
    "tv": 0,
    "oneshot": false
  },
  {
    "id": 1778054421268,
    "t": "Токийские мстители",
    "series": "Токийские мстители",
    "a": [
      "Кэн Вакуи"
    ],
    "v": 9,
    "p": 396,
    "y": "2023",
    "isbn": "9785919964490",
    "c": "https://i.postimg.cc/Hkw26QgM/009.png",
    "pub": "XL Media",
    "g": [
      "Сёнен",
      "Экшен"
    ],
    "tv": 0,
    "oneshot": false
  },
  {
    "id": 1778054470282,
    "t": "Токийские мстители",
    "series": "Токийские мстители",
    "a": [
      "Кэн Вакуи"
    ],
    "v": 10,
    "p": 386,
    "y": "2023",
    "isbn": "9785919964506",
    "c": "https://i.postimg.cc/0yYfVpsp/010.png",
    "pub": "XL Media",
    "g": [
      "Сёнен",
      "Экшен"
    ],
    "tv": 0,
    "oneshot": false
  },
  {
    "id": 1778054559089,
    "t": "Токийские мстители",
    "series": "Токийские мстители",
    "a": [
      "Кэн Вакуи"
    ],
    "v": 11,
    "p": 368,
    "y": "2023",
    "isbn": "9785919964667",
    "c": "https://i.postimg.cc/8Prwr2X7/011.webp",
    "pub": "XL Media",
    "g": [
      "Сёнен",
      "Экшен"
    ],
    "tv": 0,
    "oneshot": false
  },
  {
    "id": 1778054610756,
    "t": "Токийские мстители",
    "series": "Токийские мстители",
    "a": [
      "Кэн Вакуи"
    ],
    "v": 12,
    "p": 368,
    "y": "2023",
    "isbn": "9785919964650",
    "c": "https://i.postimg.cc/zXRpRs2c/012.webp",
    "pub": "XL Media",
    "g": [
      "Сёнен",
      "Экшен"
    ],
    "tv": 0,
    "oneshot": false
  },
  {
    "id": "1778581924779",
    "t": "Старина",
    "series": "Старина",
    "a": [
      "Гарон Цутия",
      "Нобуаки Минэгиси"
    ],
    "g": [
      "Сэйнэн",
      "Экшен",
      "Драма",
      "Тайна"
    ],
    "v": 1,
    "p": 416,
    "y": "2023",
    "isbn": "9785907576261",
    "pub": "Alt Graph",
    "c": "https://i.postimg.cc/5t9nCFn4/001.jpg",
    "tv": 0,
    "oneshot": false
  },
  {
    "id": "1778582132561",
    "t": "Старина",
    "series": "Старина",
    "a": [
      "Гарон Цутия",
      "Нобуаки Минэгиси"
    ],
    "g": [
      "Сэйнэн",
      "Экшен",
      "Драма",
      "Тайна"
    ],
    "v": 2,
    "p": 420,
    "y": "2023",
    "isbn": "9785907576278",
    "pub": "Alt Graph",
    "c": "https://i.postimg.cc/Mpm9HYbx/002.jpg",
    "tv": 0,
    "oneshot": false
  },
  {
    "id": 1778354093603,
    "t": "Созданный в Бездне",
    "series": "Созданный в Бездне",
    "a": [
      "Цукуси Акихито"
    ],
    "v": 3,
    "p": 160,
    "y": "2019",
    "isbn": "9785171151270",
    "c": "https://i.postimg.cc/cHYT7pmF/003.jpg",
    "pub": "Reanimedia",
    "g": [
      "Приключения",
      "Драма",
      "Фэнтези",
      "Фантастика"
    ],
    "tv": 0,
    "oneshot": false
  },
  {
    "id": 1778396748912,
    "t": "Созданный в Бездне",
    "series": "Созданный в Бездне",
    "a": [
      "Цукуси Акихито"
    ],
    "v": 2,
    "p": 160,
    "y": "2019",
    "isbn": "9785171153205",
    "c": "https://i.postimg.cc/RFfG1kRX/002.jpg",
    "pub": "Reanimedia",
    "g": [
      "Приключения",
      "Драма",
      "Фэнтези",
      "Фантастика"
    ],
    "tv": 0,
    "oneshot": false
  },
  {
    "id": 1778396839319,
    "t": "Созданный в Бездне",
    "series": "Созданный в Бездне",
    "a": [
      "Цукуси Акихито"
    ],
    "v": 4,
    "p": 160,
    "y": "2019",
    "isbn": "9785171172039",
    "c": "https://i.postimg.cc/GtCKXX7Y/004.jpg",
    "pub": "Reanimedia",
    "g": [
      "Приключения",
      "Драма",
      "Фэнтези",
      "Фантастика"
    ],
    "tv": 0,
    "oneshot": false
  },
  {
    "id": 1778396892139,
    "t": "Созданный в Бездне",
    "series": "Созданный в Бездне",
    "a": [
      "Цукуси Акихито"
    ],
    "v": 5,
    "p": 160,
    "y": "2019",
    "isbn": "9785171188191",
    "c": "https://i.postimg.cc/Wzv855WG/005.jpg",
    "pub": "Reanimedia",
    "g": [
      "Приключения",
      "Драма",
      "Фэнтези",
      "Фантастика"
    ],
    "tv": 0,
    "oneshot": false
  },
  {
    "id": 1778420682144,
    "t": "Созданный в Бездне",
    "series": "Созданный в Бездне",
    "a": [
      "Цукуси Акихито"
    ],
    "v": 6,
    "p": 160,
    "y": "2020",
    "isbn": "9785171192686",
    "c": "https://i.postimg.cc/L5pDxxCk/006.jpg",
    "pub": "Reanimedia",
    "g": [
      "Приключения",
      "Драма",
      "Фэнтези",
      "Фантастика"
    ],
    "tv": 0,
    "oneshot": false
  },
  {
    "id": 1778420766400,
    "t": "Созданный в Бездне",
    "series": "Созданный в Бездне",
    "a": [
      "Цукуси Акихито"
    ],
    "v": 7,
    "p": 160,
    "y": "2020",
    "isbn": "9785171208288",
    "c": "https://i.postimg.cc/RhBdggsQ/007.jpg",
    "pub": "Reanimedia",
    "g": [
      "Приключения",
      "Драма",
      "Фэнтези",
      "Фантастика"
    ],
    "tv": 0,
    "oneshot": false
  },
  {
    "id": 1778420827797,
    "t": "Созданный в Бездне",
    "series": "Созданный в Бездне",
    "a": [
      "Цукуси Акихито"
    ],
    "v": 8,
    "p": 160,
    "y": "2020",
    "isbn": "9785171208295",
    "c": "https://i.postimg.cc/gjWsggSH/008.jpg",
    "pub": "Reanimedia",
    "g": [
      "Приключения",
      "Драма",
      "Фэнтези",
      "Фантастика"
    ],
    "tv": 0,
    "oneshot": false
  },
  {
    "id": 1778420911011,
    "t": "Созданный в Бездне",
    "series": "Созданный в Бездне",
    "a": [
      "Цукуси Акихито"
    ],
    "v": 9,
    "p": 160,
    "y": "2021",
    "isbn": "9785171368722",
    "c": "https://i.postimg.cc/prHCssGk/009.jpg",
    "pub": "Reanimedia",
    "g": [
      "Приключения",
      "Драма",
      "Фэнтези",
      "Фантастика"
    ],
    "tv": 0,
    "oneshot": false
  },
  {
    "id": 1778396674843,
    "t": "Созданный в Бездне",
    "series": "Созданный в Бездне",
    "a": [
      "Цукуси Акихито"
    ],
    "v": 1,
    "p": 168,
    "y": "2019",
    "isbn": "9785171153199",
    "c": "https://i.postimg.cc/wvJF5CVF/001.jpg",
    "pub": "Reanimedia",
    "g": [
      "Приключения",
      "Драма",
      "Фэнтези",
      "Фантастика"
    ],
    "tv": 0,
    "oneshot": false
  },
  {
    "id": 1777827273448,
    "t": "Семья шпиона",
    "series": "Семья шпиона",
    "a": [
      "Тацуя Эндо"
    ],
    "v": 1,
    "p": 212,
    "y": "2022",
    "isbn": "9785604723593",
    "c": "https://i.postimg.cc/JhDzn4Kv/001.jpg",
    "pub": "Истари Комикс",
    "g": [
      "Сёнен",
      "Экшен",
      "Комедия"
    ],
    "tv": 0,
    "oneshot": false
  },
  {
    "id": 1777827628379,
    "t": "Семья шпиона",
    "series": "Семья шпиона",
    "a": [
      "Тацуя Эндо"
    ],
    "v": 2,
    "p": 194,
    "y": "2022",
    "isbn": "9785907539006",
    "c": "https://i.postimg.cc/zfbGBXp4/002.jpg",
    "pub": "Истари Комикс",
    "g": [
      "Сёнен",
      "Экшен",
      "Комедия"
    ],
    "tv": 0,
    "oneshot": false
  },
  {
    "id": 1777832991496,
    "t": "Семья шпиона",
    "series": "Семья шпиона",
    "a": [
      "Тацуя Эндо"
    ],
    "v": 3,
    "p": 194,
    "y": "2022",
    "isbn": "9785907539013",
    "c": "https://i.postimg.cc/Pqp5xr2G/003.jpg",
    "pub": "Истари Комикс",
    "g": [
      "Сёнен",
      "Экшен",
      "Комедия"
    ],
    "tv": 0,
    "oneshot": false
  },
  {
    "id": 1778056600069,
    "t": "Семья шпиона",
    "series": "Семья шпиона",
    "a": [
      "Тацуя Эндо"
    ],
    "v": 4,
    "p": 186,
    "y": "2023",
    "isbn": "9785907539426",
    "c": "https://i.postimg.cc/25bS682N/004.jpg",
    "pub": "Истари Комикс",
    "g": [
      "Сёнен",
      "Экшен",
      "Комедия"
    ],
    "tv": 0,
    "oneshot": false
  },
  {
    "id": 1778056737678,
    "t": "Семья шпиона",
    "series": "Семья шпиона",
    "a": [
      "Тацуя Эндо"
    ],
    "v": 5,
    "p": 202,
    "y": "2023",
    "isbn": "9785907539433",
    "c": "https://i.postimg.cc/CK3LfTQf/005.jpg",
    "pub": "Истари Комикс",
    "g": [
      "Сёнен",
      "Экшен",
      "Комедия"
    ],
    "tv": 0,
    "oneshot": false
  },
  {
    "id": 1778056792225,
    "t": "Семья шпиона",
    "series": "Семья шпиона",
    "a": [
      "Тацуя Эндо"
    ],
    "v": 6,
    "p": 202,
    "y": "2023",
    "isbn": "9785907539440",
    "c": "https://i.postimg.cc/HLqs7Dhj/006.jpg",
    "pub": "Истари Комикс",
    "g": [
      "Сёнен",
      "Экшен",
      "Комедия"
    ],
    "tv": 0,
    "oneshot": false
  },
  {
    "id": 1778056852064,
    "t": "Семья шпиона",
    "series": "Семья шпиона",
    "a": [
      "Тацуя Эндо"
    ],
    "v": 7,
    "p": 194,
    "y": "2023",
    "isbn": "9785907539815",
    "c": "https://i.postimg.cc/cJp48ybw/007.jpg",
    "pub": "Истари Комикс",
    "g": [
      "Сёнен",
      "Экшен",
      "Комедия"
    ],
    "tv": 0,
    "oneshot": false
  },
  {
    "id": 1778056966343,
    "t": "Семья шпиона",
    "series": "Семья шпиона",
    "a": [
      "Тацуя Эндо"
    ],
    "v": 8,
    "p": 210,
    "y": "2023",
    "isbn": "9785907539822",
    "c": "https://i.postimg.cc/ZqGKytMr/008.jpg",
    "pub": "Истари Комикс",
    "g": [
      "Сёнен",
      "Экшен",
      "Комедия"
    ],
    "tv": 0,
    "oneshot": false
  },
  {
    "id": 1778057187592,
    "t": "Семья шпиона",
    "series": "Семья шпиона",
    "a": [
      "Тацуя Эндо"
    ],
    "v": 10,
    "p": 194,
    "y": "2023",
    "isbn": "9785907539846",
    "c": "https://i.postimg.cc/W4BbJLH5/010.jpg",
    "pub": "Истари Комикс",
    "g": [
      "Сёнен",
      "Экшен",
      "Комедия"
    ],
    "tv": 0,
    "oneshot": false
  },
  {
    "id": 1778057283204,
    "t": "Семья шпиона",
    "series": "Семья шпиона",
    "a": [
      "Тацуя Эндо"
    ],
    "v": 9,
    "p": 210,
    "y": "2023",
    "isbn": "9785907539839",
    "c": "https://i.postimg.cc/GpWhsw5q/009.jpg",
    "pub": "Истари Комикс",
    "g": [
      "Сёнен",
      "Экшен",
      "Комедия"
    ],
    "tv": 0,
    "oneshot": false
  },
  {
    "id": 1778057407682,
    "t": "Семья шпиона",
    "series": "Семья шпиона",
    "a": [
      "Тацуя Эндо"
    ],
    "v": 11,
    "p": 202,
    "y": "2025",
    "isbn": "9785907775510",
    "c": "https://i.postimg.cc/Jnj7N6fc/011.jpg",
    "pub": "Истари Комикс",
    "g": [
      "Сёнен",
      "Экшен",
      "Комедия"
    ],
    "tv": 0,
    "oneshot": false
  },
  {
    "id": 1778057468728,
    "t": "Семья шпиона",
    "series": "Семья шпиона",
    "a": [
      "Тацуя Эндо"
    ],
    "v": 12,
    "p": 202,
    "y": "2025",
    "isbn": "9785907775527",
    "c": "https://i.postimg.cc/sX5fY6kJ/012.jpg",
    "pub": "Истари Комикс",
    "g": [
      "Сёнен",
      "Экшен",
      "Комедия"
    ],
    "tv": 0,
    "oneshot": false
  },
  {
    "id": 1778057644582,
    "t": "Семья шпиона",
    "series": "Семья шпиона",
    "a": [
      "Тацуя Эндо"
    ],
    "v": 13,
    "p": 194,
    "y": "2025",
    "isbn": "9785907775534",
    "c": "https://i.postimg.cc/76SP3sF9/013.jpg",
    "pub": "Истари Комикс",
    "g": [
      "Сёнен",
      "Экшен",
      "Комедия"
    ],
    "tv": 0,
    "oneshot": false
  },
  {
    "id": 1778057749442,
    "t": "Семья шпиона",
    "series": "Семья шпиона",
    "a": [
      "Тацуя Эндо"
    ],
    "v": 14,
    "p": 194,
    "y": "2025",
    "isbn": "9785907775541",
    "c": "https://i.postimg.cc/9MyXd861/014.jpg",
    "pub": "Истари Комикс",
    "g": [
      "Сёнен",
      "Экшен",
      "Комедия"
    ],
    "tv": 0,
    "oneshot": false
  },
  {
    "id": 1778522730952,
    "t": "Призрак в доспехах",
    "series": "Призрак в доспехах",
    "a": [
      "Сиро Масамунэ"
    ],
    "v": 3,
    "p": 184,
    "y": "2022",
    "isbn": "9785389183506",
    "c": "https://i.postimg.cc/W40RMhLz/001-5.jpg",
    "pub": "Азбука",
    "g": [
      "Сэйнэн",
      "Экшен",
      "Фантастика"
    ],
    "tv": 0,
    "oneshot": false
  },
  {
    "id": 1778522825675,
    "t": "Призрак в доспехах",
    "series": "Призрак в доспехах",
    "a": [
      "Сиро Масамунэ"
    ],
    "v": 2,
    "p": 308,
    "y": "2021",
    "isbn": "9785389159013",
    "c": "https://i.postimg.cc/6QCsdyJf/002.jpg",
    "pub": "Азбука",
    "g": [
      "Сэйнэн",
      "Экшен",
      "Фантастика"
    ],
    "tv": 0,
    "oneshot": false
  },
  {
    "id": 1778522941549,
    "t": "Призрак в доспехах",
    "series": "Призрак в доспехах",
    "a": [
      "Сиро Масамунэ"
    ],
    "v": 1,
    "p": 352,
    "y": "2020",
    "isbn": "9785389134645",
    "c": "https://i.postimg.cc/SKc0WJFV/001.jpg",
    "pub": "Азбука",
    "g": [
      "Сэйнэн",
      "Экшен",
      "Фантастика"
    ],
    "tv": 0,
    "oneshot": false
  },
  {
    "id": "1777402257167",
    "t": "Признание",
    "series": "Признание",
    "a": [
      "Нобуюки Фукумото"
    ],
    "g": [
      "Сэйнэн",
      "Драма",
      "Триллер"
    ],
    "v": 1,
    "tv": 1,
    "oneshot": true,
    "p": 312,
    "y": "2025",
    "isbn": "9785042187544",
    "pub": "Комильфо",
    "c": "https://i.postimg.cc/431w8Js6/00002.webp"
  },
  {
    "id": "1777406480910",
    "t": "Преследовательница",
    "series": "Преследовательница",
    "a": [
      "Минэтаро Мотидзуки"
    ],
    "g": [
      "Сэйнэн",
      "Драма",
      "Ужасы"
    ],
    "v": 1,
    "tv": 1,
    "oneshot": true,
    "p": 212,
    "y": "2025",
    "isbn": "9785042130755",
    "pub": "Комильфо",
    "c": "https://i.postimg.cc/vBry2xDq/00001.webp"
  },
  {
    "id": 1777410242929,
    "t": "По велению высших сил",
    "series": "По велению высших сил",
    "a": [
      "Мунэюки Канэсиро",
      "Акэдзи Фудзимура"
    ],
    "v": 1,
    "p": 224,
    "y": "2025",
    "isbn": "9785042151262",
    "c": "https://i.postimg.cc/fTKKHHwf/001.webp",
    "pub": "Комильфо",
    "g": [
      "Сёнен",
      "Экшен",
      "Сверхъестественное"
    ],
    "tv": 0,
    "oneshot": false
  },
  {
    "id": 1777410446962,
    "t": "По велению высших сил",
    "series": "По велению высших сил",
    "a": [
      "Мунэюки Канэсиро",
      "Акэдзи Фудзимура"
    ],
    "v": 2,
    "p": 200,
    "y": "2025",
    "isbn": "9785042285554",
    "c": "https://i.postimg.cc/X78822VH/002.webp",
    "pub": "Комильфо",
    "g": [
      "Сёнен",
      "Экшен",
      "Сверхъестественное"
    ],
    "tv": 0,
    "oneshot": false
  },
  {
    "id": 1777389880171,
    "t": "Огненный удар",
    "series": "Огненный удар",
    "a": [
      "Тацуки Фудзимото"
    ],
    "v": 1,
    "p": 416,
    "y": "2023",
    "isbn": "9785389226388",
    "c": "https://i.postimg.cc/dtdg701g/001.jpg",
    "pub": "Азбука",
    "g": [
      "Сёнен",
      "Экшен",
      "Тайна"
    ],
    "tv": 0,
    "oneshot": false
  },
  {
    "id": 1777394805142,
    "t": "Огненный удар",
    "series": "Огненный удар",
    "a": [
      "Тацуки Фудзимото"
    ],
    "v": 2,
    "p": 416,
    "y": "2023",
    "isbn": "9785389228412",
    "c": "https://i.postimg.cc/wTJntBvw/002.jpg",
    "pub": "Азбука",
    "g": [
      "Сёнен",
      "Экшен",
      "Тайна"
    ],
    "tv": 0,
    "oneshot": false
  },
  {
    "id": 1777748767687,
    "t": "Огненный удар",
    "series": "Огненный удар",
    "a": [
      "Тацуки Фудзимото"
    ],
    "v": 3,
    "p": 416,
    "y": "2023",
    "isbn": "9785389232433",
    "c": "https://i.postimg.cc/RVf230Fy/003.jpg",
    "pub": "Азбука",
    "g": [
      "Сёнен",
      "Экшен",
      "Тайна"
    ],
    "tv": 0,
    "oneshot": false
  },
  {
    "id": 1777748941557,
    "t": "Огненный удар",
    "series": "Огненный удар",
    "a": [
      "Тацуки Фудзимото"
    ],
    "v": 4,
    "p": 416,
    "y": "2023",
    "isbn": "9785389234222",
    "c": "https://i.postimg.cc/m2MKcrDn/004.jpg",
    "pub": "Азбука",
    "g": [
      "Сёнен",
      "Экшен",
      "Тайна"
    ],
    "tv": 0,
    "oneshot": false
  },
  {
    "id": 1778424011032,
    "t": "Обещанная страна грёз",
    "series": "Обещанная страна грёз",
    "a": [
      "Каиу Сираи",
      "Поска Дэмидзу"
    ],
    "v": 1,
    "p": 384,
    "y": "2020",
    "isbn": "9785604344460",
    "c": "https://i.postimg.cc/KY8PrBt5/001.jpg",
    "pub": "Истари Комикс",
    "g": [
      "Сёнен",
      "Тайна",
      "Триллер"
    ],
    "tv": 0,
    "oneshot": false
  },
  {
    "id": 1778424320491,
    "t": "Обещанная страна грёз",
    "series": "Обещанная страна грёз",
    "a": [
      "Каиу Сираи",
      "Поска Дэмидзу"
    ],
    "v": 2,
    "p": 392,
    "y": "2020",
    "isbn": "9785604344477",
    "c": "https://i.postimg.cc/FKHyg30y/002.jpg",
    "pub": "Истари Комикс",
    "g": [
      "Сёнен",
      "Тайна",
      "Триллер"
    ],
    "tv": 0,
    "oneshot": false
  },
  {
    "id": 1778424510121,
    "t": "Обещанная страна грёз",
    "series": "Обещанная страна грёз",
    "a": [
      "Каиу Сираи",
      "Поска Дэмидзу"
    ],
    "v": 3,
    "p": 400,
    "y": "2021",
    "isbn": "9785907340121",
    "c": "https://i.postimg.cc/d0V2mrG6/003.jpg",
    "pub": "Истари Комикс",
    "g": [
      "Сёнен",
      "Тайна",
      "Триллер"
    ],
    "tv": 0,
    "oneshot": false
  },
  {
    "id": 1778424549652,
    "t": "Обещанная страна грёз",
    "series": "Обещанная страна грёз",
    "a": [
      "Каиу Сираи",
      "Поска Дэмидзу"
    ],
    "v": 4,
    "p": 384,
    "y": "2021",
    "isbn": "9785907340138",
    "c": "https://i.postimg.cc/hGtLbTV9/004.jpg",
    "pub": "Истари Комикс",
    "g": [
      "Сёнен",
      "Тайна",
      "Триллер"
    ],
    "tv": 0,
    "oneshot": false
  },
  {
    "id": 1778424599996,
    "t": "Обещанная страна грёз",
    "series": "Обещанная страна грёз",
    "a": [
      "Каиу Сираи",
      "Поска Дэмидзу"
    ],
    "v": 5,
    "p": 384,
    "y": "2021",
    "isbn": "9785907340145",
    "c": "https://i.postimg.cc/W4YM9z7r/005.jpg",
    "pub": "Истари Комикс",
    "g": [
      "Сёнен",
      "Тайна",
      "Триллер"
    ],
    "tv": 0,
    "oneshot": false
  },
  {
    "id": 1778424727059,
    "t": "Обещанная страна грёз",
    "series": "Обещанная страна грёз",
    "a": [
      "Каиу Сираи",
      "Поска Дэмидзу"
    ],
    "v": 6,
    "p": 388,
    "y": "2022",
    "isbn": "9785604344484",
    "c": "https://i.postimg.cc/5tKwPymB/006.jpg",
    "pub": "Истари Комикс",
    "g": [
      "Сёнен",
      "Тайна",
      "Триллер"
    ],
    "tv": 0,
    "oneshot": false
  },
  {
    "id": 1778424782042,
    "t": "Обещанная страна грёз",
    "series": "Обещанная страна грёз",
    "a": [
      "Каиу Сираи",
      "Поска Дэмидзу"
    ],
    "v": 7,
    "p": 388,
    "y": "2022",
    "isbn": "9785907340640",
    "c": "https://i.postimg.cc/q7D8mqGG/007.jpg",
    "pub": "Истари Комикс",
    "g": [
      "Сёнен",
      "Тайна",
      "Триллер"
    ],
    "tv": 0,
    "oneshot": false
  },
  {
    "id": 1778424834504,
    "t": "Обещанная страна грёз",
    "series": "Обещанная страна грёз",
    "a": [
      "Каиу Сираи",
      "Поска Дэмидзу"
    ],
    "v": 8,
    "p": 400,
    "y": "2023",
    "isbn": "9785907539464",
    "c": "https://i.postimg.cc/9fgGx0B1/008.jpg",
    "pub": "Истари Комикс",
    "g": [
      "Сёнен",
      "Тайна",
      "Триллер"
    ],
    "tv": 0,
    "oneshot": false
  },
  {
    "id": 1778424880163,
    "t": "Обещанная страна грёз",
    "series": "Обещанная страна грёз",
    "a": [
      "Каиу Сираи",
      "Поска Дэмидзу"
    ],
    "v": 10,
    "p": 452,
    "y": "2023",
    "isbn": "9785907539754",
    "c": "https://i.postimg.cc/ZqsrfnLs/010.jpg",
    "pub": "Истари Комикс",
    "g": [
      "Сёнен",
      "Тайна",
      "Триллер"
    ],
    "tv": 0,
    "oneshot": false
  },
  {
    "id": 1778424916732,
    "t": "Обещанная страна грёз",
    "series": "Обещанная страна грёз",
    "a": [
      "Каиу Сираи",
      "Поска Дэмидзу"
    ],
    "v": 9,
    "p": 388,
    "y": "2023",
    "isbn": "9785907539747",
    "c": "https://i.postimg.cc/Xv1w2qg8/009.jpg",
    "pub": "Истари Комикс",
    "g": [
      "Сёнен",
      "Тайна",
      "Триллер"
    ],
    "tv": 0,
    "oneshot": false
  },
  {
    "id": 1778063708784,
    "t": "Монолог фармацевта",
    "series": "Монолог фармацевта",
    "a": [
      "Хюганацу",
      "Nekokurage",
      "Ицуки Нанао",
      "Токо Сино"
    ],
    "v": 1,
    "p": 366,
    "y": "2025",
    "isbn": "9785919965329",
    "c": "https://i.postimg.cc/9FjHXhQy/001.jpg",
    "pub": "XL Media",
    "g": [
      "Сэйнэн",
      "Драма",
      "Тайна"
    ],
    "tv": 0,
    "oneshot": false
  },
  {
    "id": 1778067838484,
    "t": "Монолог фармацевта",
    "series": "Монолог фармацевта",
    "a": [
      "Хюганацу",
      "Nekokurage",
      "Ицуки Нанао",
      "Токо Сино"
    ],
    "v": 2,
    "p": 398,
    "y": "2025",
    "isbn": "9785919965459",
    "c": "https://i.postimg.cc/L6MF4p8z/002.jpg",
    "pub": "XL Media",
    "g": [
      "Сэйнэн",
      "Драма",
      "Тайна"
    ],
    "tv": 0,
    "oneshot": false
  },
  {
    "id": 1778079320919,
    "t": "Монолог фармацевта",
    "series": "Монолог фармацевта",
    "a": [
      "Хюганацу",
      "Nekokurage",
      "Ицуки Нанао",
      "Токо Сино"
    ],
    "v": 3,
    "p": 358,
    "y": "2025",
    "isbn": "9785919965473",
    "c": "https://i.postimg.cc/m2GWZsgY/003.jpg",
    "pub": "XL Media",
    "g": [
      "Сэйнэн",
      "Драма",
      "Тайна"
    ],
    "tv": 0,
    "oneshot": false
  },
  {
    "id": 1778079400138,
    "t": "Монолог фармацевта",
    "series": "Монолог фармацевта",
    "a": [
      "Хюганацу",
      "Nekokurage",
      "Ицуки Нанао",
      "Токо Сино"
    ],
    "v": 4,
    "p": 364,
    "y": "2025",
    "isbn": "9785919965565",
    "c": "https://i.postimg.cc/Gh1n3Cmx/004.jpg",
    "pub": "XL Media",
    "g": [
      "Сэйнэн",
      "Драма",
      "Тайна"
    ],
    "tv": 0,
    "oneshot": false
  },
  {
    "id": 1778079443546,
    "t": "Монолог фармацевта",
    "series": "Монолог фармацевта",
    "a": [
      "Хюганацу",
      "Nekokurage",
      "Ицуки Нанао",
      "Токо Сино"
    ],
    "v": 5,
    "p": 362,
    "y": "2026",
    "isbn": "9785919965602",
    "c": "https://i.postimg.cc/QxrZN3d1/005.jpg",
    "pub": "XL Media",
    "g": [
      "Сэйнэн",
      "Драма",
      "Тайна"
    ],
    "tv": 0,
    "oneshot": false
  },
  {
    "id": 1778079537554,
    "t": "Монолог фармацевта",
    "series": "Монолог фармацевта",
    "a": [
      "Хюганацу",
      "Nekokurage",
      "Ицуки Нанао",
      "Токо Сино"
    ],
    "v": 6,
    "p": 358,
    "y": "2026",
    "isbn": "9785919965336",
    "c": "https://i.postimg.cc/HsC1Wgk4/006.jpg",
    "pub": "XL Media",
    "g": [
      "Сэйнэн",
      "Драма",
      "Тайна"
    ],
    "tv": 0,
    "oneshot": false
  },
  {
    "id": 1778518681891,
    "t": "Крутой учитель Онидзука",
    "series": "Крутой учитель Онидзука",
    "a": [
      "Тору Фудзисава"
    ],
    "v": 1,
    "p": 568,
    "y": "2021",
    "isbn": "9785041116767",
    "c": "https://i.postimg.cc/DzJkmS0x/001.jpg",
    "pub": "Комильфо",
    "g": [
      "Сёнен",
      "Экшен",
      "Комедия",
      "Драма",
      "Этти"
    ],
    "tv": 0,
    "oneshot": false
  },
  {
    "id": 1778518803097,
    "t": "Крутой учитель Онидзука",
    "series": "Крутой учитель Онидзука",
    "a": [
      "Тору Фудзисава"
    ],
    "v": 2,
    "p": 560,
    "y": "2022",
    "isbn": "9785041583873",
    "c": "https://i.postimg.cc/25spWCLg/002.jpg",
    "pub": "Комильфо",
    "g": [
      "Сёнен",
      "Экшен",
      "Комедия",
      "Драма",
      "Этти"
    ],
    "tv": 0,
    "oneshot": false
  },
  {
    "id": 1778518880510,
    "t": "Крутой учитель Онидзука",
    "series": "Крутой учитель Онидзука",
    "a": [
      "Тору Фудзисава"
    ],
    "v": 3,
    "p": 560,
    "y": "2023",
    "isbn": "9785041725730",
    "c": "https://i.postimg.cc/hGkFmK74/003.jpg",
    "pub": "Комильфо",
    "g": [
      "Сёнен",
      "Экшен",
      "Комедия",
      "Драма",
      "Этти"
    ],
    "tv": 0,
    "oneshot": false
  },
  {
    "id": 1778518943839,
    "t": "Крутой учитель Онидзука",
    "series": "Крутой учитель Онидзука",
    "a": [
      "Тору Фудзисава"
    ],
    "v": 4,
    "p": 560,
    "y": "2023",
    "isbn": "9785041749361",
    "c": "https://i.postimg.cc/T1cBBm77/004.jpg",
    "pub": "Комильфо",
    "g": [
      "Сёнен",
      "Экшен",
      "Комедия",
      "Драма",
      "Этти"
    ],
    "tv": 0,
    "oneshot": false
  },
  {
    "id": 1778519386794,
    "t": "Крутой учитель Онидзука",
    "series": "Крутой учитель Онидзука",
    "a": [
      "Тору Фудзисава"
    ],
    "v": 5,
    "p": 584,
    "y": "2024",
    "isbn": "9785041841690",
    "c": "https://i.postimg.cc/HntFF5vp/005.jpg",
    "pub": "Комильфо",
    "g": [
      "Сёнен",
      "Экшен",
      "Комедия",
      "Драма",
      "Этти"
    ],
    "tv": 0,
    "oneshot": false
  },
  {
    "id": 1778519440739,
    "t": "Крутой учитель Онидзука",
    "series": "Крутой учитель Онидзука",
    "a": [
      "Тору Фудзисава"
    ],
    "v": 6,
    "p": 568,
    "y": "2024",
    "isbn": "9785041918460",
    "c": "https://i.postimg.cc/05dg6RkX/006.jpg",
    "pub": "Комильфо",
    "g": [
      "Сёнен",
      "Экшен",
      "Комедия",
      "Драма",
      "Этти"
    ],
    "tv": 0,
    "oneshot": false
  },
  {
    "id": 1778519505042,
    "t": "Крутой учитель Онидзука",
    "series": "Крутой учитель Онидзука",
    "a": [
      "Тору Фудзисава"
    ],
    "v": 7,
    "p": 560,
    "y": "2025",
    "isbn": "9785042163326",
    "c": "https://i.postimg.cc/5yxfHfZx/007.jpg",
    "pub": "Комильфо",
    "g": [
      "Сёнен",
      "Экшен",
      "Комедия",
      "Драма",
      "Этти"
    ],
    "tv": 0,
    "oneshot": false
  },
  {
    "id": 1778519552451,
    "t": "Крутой учитель Онидзука",
    "series": "Крутой учитель Онидзука",
    "a": [
      "Тору Фудзисава"
    ],
    "v": 8,
    "p": 400,
    "y": "2025",
    "isbn": "9785042053191",
    "c": "https://i.postimg.cc/VsBySQfx/008.jpg",
    "pub": "Комильфо",
    "g": [
      "Сёнен",
      "Экшен",
      "Комедия",
      "Драма",
      "Этти"
    ],
    "tv": 0,
    "oneshot": false
  },
  {
    "id": 1778519596769,
    "t": "Крутой учитель Онидзука",
    "series": "Крутой учитель Онидзука",
    "a": [
      "Тору Фудзисава"
    ],
    "v": 9,
    "p": 400,
    "y": "2025",
    "isbn": "9785042055966",
    "c": "https://i.postimg.cc/fTwGm2y6/009.jpg",
    "pub": "Комильфо",
    "g": [
      "Сёнен",
      "Экшен",
      "Комедия",
      "Драма",
      "Этти"
    ],
    "tv": 0,
    "oneshot": false
  },
  {
    "id": "1778531638879",
    "t": "За чашечкой кофе",
    "series": "За чашечкой кофе",
    "a": [
      "Тэцуя Тоёда"
    ],
    "g": [
      "Сэйнэн",
      "Комедия",
      "Повседневность"
    ],
    "v": 1,
    "tv": 1,
    "oneshot": true,
    "p": 208,
    "y": "2025",
    "isbn": "9785042272172",
    "pub": "Комильфо",
    "c": "https://i.postimg.cc/gc3TNnJh/00004.jpg"
  },
  {
    "id": 1778434344925,
    "t": "Девочка из Чужеземья",
    "series": "Девочка из Чужеземья",
    "a": [
      "Нагабэ"
    ],
    "v": 1,
    "p": 178,
    "y": "2017",
    "isbn": "9785904676940",
    "c": "https://i.postimg.cc/fyzLym8x/001.jpg",
    "pub": "Истари Комикс",
    "g": [
      "Сёнен",
      "Фэнтези"
    ],
    "tv": 0,
    "oneshot": false
  },
  {
    "id": 1778434386114,
    "t": "Девочка из Чужеземья",
    "series": "Девочка из Чужеземья",
    "a": [
      "Нагабэ"
    ],
    "v": 2,
    "p": 178,
    "y": "2017",
    "isbn": "9785904676957",
    "c": "https://i.postimg.cc/SRSsRCgc/002.jpg",
    "pub": "Истари Комикс",
    "g": [
      "Сёнен",
      "Фэнтези"
    ],
    "tv": 0,
    "oneshot": false
  },
  {
    "id": 1778434448920,
    "t": "Девочка из Чужеземья",
    "series": "Девочка из Чужеземья",
    "a": [
      "Нагабэ"
    ],
    "v": 3,
    "p": 178,
    "y": "2018",
    "isbn": "9785907014183",
    "c": "https://i.postimg.cc/MTbHzdmP/003.jpg",
    "pub": "Истари Комикс",
    "g": [
      "Сёнен",
      "Фэнтези"
    ],
    "tv": 0,
    "oneshot": false
  },
  {
    "id": 1778434542916,
    "t": "Девочка из Чужеземья",
    "series": "Девочка из Чужеземья",
    "a": [
      "Нагабэ"
    ],
    "v": 4,
    "p": 178,
    "y": "2018",
    "isbn": "9785907014275",
    "c": "https://i.postimg.cc/cHMCdXBh/004.jpg",
    "pub": "Истари Комикс",
    "g": [
      "Сёнен",
      "Фэнтези"
    ],
    "tv": 0,
    "oneshot": false
  },
  {
    "id": 1778434614546,
    "t": "Девочка из Чужеземья",
    "series": "Девочка из Чужеземья",
    "a": [
      "Нагабэ"
    ],
    "v": 5,
    "p": 178,
    "y": "2019",
    "isbn": "9785907014428",
    "c": "https://i.postimg.cc/D0vZ0Lxr/005.jpg",
    "pub": "Истари Комикс",
    "g": [
      "Сёнен",
      "Фэнтези"
    ],
    "tv": 0,
    "oneshot": false
  },
  {
    "id": 1778434679782,
    "t": "Девочка из Чужеземья",
    "series": "Девочка из Чужеземья",
    "a": [
      "Нагабэ"
    ],
    "v": 6,
    "p": 178,
    "y": "2020",
    "isbn": "9785907340206",
    "c": "https://i.postimg.cc/HnYxnX62/006.jpg",
    "pub": "Истари Комикс",
    "g": [
      "Сёнен",
      "Фэнтези"
    ],
    "tv": 0,
    "oneshot": false
  },
  {
    "id": 1778434717962,
    "t": "Девочка из Чужеземья",
    "series": "Девочка из Чужеземья",
    "a": [
      "Нагабэ"
    ],
    "v": 7,
    "p": 178,
    "y": "2020",
    "isbn": "9785907340213",
    "c": "https://i.postimg.cc/J0rn0ZpT/007.jpg",
    "pub": "Истари Комикс",
    "g": [
      "Сёнен",
      "Фэнтези"
    ],
    "tv": 0,
    "oneshot": false
  },
  {
    "id": 1778434752661,
    "t": "Девочка из Чужеземья",
    "series": "Девочка из Чужеземья",
    "a": [
      "Нагабэ"
    ],
    "v": 8,
    "p": 178,
    "y": "2020",
    "isbn": "9785907340220",
    "c": "https://i.postimg.cc/0jkQjDVH/008.jpg",
    "pub": "Истари Комикс",
    "g": [
      "Сёнен",
      "Фэнтези"
    ],
    "tv": 0,
    "oneshot": false
  },
  {
    "id": 1778434812796,
    "t": "Девочка из Чужеземья",
    "series": "Девочка из Чужеземья",
    "a": [
      "Нагабэ"
    ],
    "v": 10,
    "p": 170,
    "y": "2022",
    "isbn": "9785907340862",
    "c": "https://i.postimg.cc/7hH6h0Bk/010.jpg",
    "pub": "Истари Комикс",
    "g": [
      "Сёнен",
      "Фэнтези"
    ],
    "tv": 0,
    "oneshot": false
  },
  {
    "id": 1778434891332,
    "t": "Девочка из Чужеземья",
    "series": "Девочка из Чужеземья",
    "a": [
      "Нагабэ"
    ],
    "v": 11,
    "p": 178,
    "y": "2022",
    "isbn": "9785907539044",
    "c": "https://i.postimg.cc/GtL2tGMR/011.jpg",
    "pub": "Истари Комикс",
    "g": [
      "Сёнен",
      "Фэнтези"
    ],
    "tv": 0,
    "oneshot": false
  },
  {
    "id": 1778437376906,
    "t": "Девочка из Чужеземья",
    "series": "Девочка из Чужеземья",
    "a": [
      "Нагабэ"
    ],
    "v": 9,
    "p": 186,
    "y": "2022",
    "isbn": "9785907340855",
    "c": "https://i.postimg.cc/hvDjvT2Y/009.jpg",
    "pub": "Истари Комикс",
    "g": [
      "Сёнен",
      "Фэнтези"
    ],
    "tv": 0,
    "oneshot": false
  },
  {
    "id": "1778532091951",
    "t": "Глупости про удаленку",
    "series": "Глупости про удаленку",
    "a": [
      "Кинтецу Ямада"
    ],
    "g": [
      "Сэйнэн",
      "Романтика"
    ],
    "v": 1,
    "tv": 1,
    "oneshot": true,
    "p": 196,
    "y": "2026",
    "isbn": "9785042382048",
    "pub": "Комильфо",
    "c": "https://i.postimg.cc/XqXXNTXT/00005.webp"
  },
  {
    "id": 1778523526003,
    "t": "Волейбол!",
    "series": "Волейбол!",
    "a": [
      "Харуити Фурудатэ"
    ],
    "v": 1,
    "p": 392,
    "y": "2025",
    "isbn": "9785389252004",
    "c": "https://i.postimg.cc/BZz0fWg4/001.jpg",
    "pub": "Азбука",
    "g": [
      "Сёнен",
      "Спорт"
    ],
    "tv": 0,
    "oneshot": false
  },
  {
    "id": 1778523622261,
    "t": "Волейбол!",
    "series": "Волейбол!",
    "a": [
      "Харуити Фурудатэ"
    ],
    "v": 2,
    "p": 400,
    "y": "2025",
    "isbn": "9785389296794",
    "c": "https://i.postimg.cc/DfNT3Vg7/002.jpg",
    "pub": "Азбука",
    "g": [
      "Сёнен",
      "Спорт"
    ],
    "tv": 0,
    "oneshot": false
  },
  {
    "id": 1778523671218,
    "t": "Волейбол!",
    "series": "Волейбол!",
    "a": [
      "Харуити Фурудатэ"
    ],
    "v": 3,
    "p": 400,
    "y": "2025",
    "isbn": "9785389296503",
    "c": "https://i.postimg.cc/Y2PHBc3W/003.jpg",
    "pub": "Азбука",
    "g": [
      "Сёнен",
      "Спорт"
    ],
    "tv": 0,
    "oneshot": false
  },
  {
    "id": 1778523713024,
    "t": "Волейбол!",
    "series": "Волейбол!",
    "a": [
      "Харуити Фурудатэ"
    ],
    "v": 4,
    "p": 384,
    "y": "2026",
    "isbn": "9785389316089",
    "c": "https://i.postimg.cc/440gRC5d/004.jpg",
    "pub": "Азбука",
    "g": [
      "Сёнен",
      "Спорт"
    ],
    "tv": 0,
    "oneshot": false
  },
  {
    "id": 1778139100533,
    "t": "Берсерк",
    "series": "Берсерк",
    "a": [
      "Кэнтаро Миура"
    ],
    "v": 1,
    "p": 458,
    "y": "2020",
    "isbn": "9785919962908",
    "c": "https://i.postimg.cc/fy6HMDMG/001.jpg",
    "pub": "XL Media",
    "g": [
      "Сэйнэн",
      "Экшен",
      "Приключения",
      "Драма",
      "Фэнтези",
      "Ужасы"
    ],
    "tv": 0,
    "oneshot": false
  },
  {
    "id": 1778259741799,
    "t": "Берсерк",
    "series": "Берсерк",
    "a": [
      "Кэнтаро Миура"
    ],
    "v": 2,
    "p": 476,
    "y": "2020",
    "isbn": "9785919962946",
    "c": "https://i.postimg.cc/qvcmHPSS/002.jpg",
    "pub": "XL Media",
    "g": [
      "Сэйнэн",
      "Экшен",
      "Приключения",
      "Драма",
      "Фэнтези",
      "Ужасы"
    ],
    "tv": 0,
    "oneshot": false
  },
  {
    "id": 1778259814391,
    "t": "Берсерк",
    "series": "Берсерк",
    "a": [
      "Кэнтаро Миура"
    ],
    "v": 3,
    "p": 468,
    "y": "2021",
    "isbn": "9785919963400",
    "c": "https://i.postimg.cc/LsHx9yMs/003.jpg",
    "pub": "XL Media",
    "g": [
      "Сэйнэн",
      "Экшен",
      "Приключения",
      "Драма",
      "Фэнтези",
      "Ужасы"
    ],
    "tv": 0,
    "oneshot": false
  },
  {
    "id": 1778262813412,
    "t": "Берсерк",
    "series": "Берсерк",
    "a": [
      "Кэнтаро Миура"
    ],
    "v": 4,
    "p": 466,
    "y": "2022",
    "isbn": "9785919963349",
    "c": "https://i.postimg.cc/CxpvthPG/004.jpg",
    "pub": "XL Media",
    "g": [
      "Сэйнэн",
      "Экшен",
      "Приключения",
      "Драма",
      "Фэнтези",
      "Ужасы"
    ],
    "tv": 0,
    "oneshot": false
  },
  {
    "id": 1778262900404,
    "t": "Берсерк",
    "series": "Берсерк",
    "a": [
      "Кэнтаро Миура"
    ],
    "v": 5,
    "p": 474,
    "y": "2022",
    "isbn": "9785919964216",
    "c": "https://i.postimg.cc/WpBLNPY1/005.jpg",
    "pub": "XL Media",
    "g": [
      "Сэйнэн",
      "Экшен",
      "Приключения",
      "Драма",
      "Фэнтези",
      "Ужасы"
    ],
    "tv": 0,
    "oneshot": false
  },
  {
    "id": 1778263211836,
    "t": "Берсерк",
    "series": "Берсерк",
    "a": [
      "Кэнтаро Миура"
    ],
    "v": 6,
    "p": 466,
    "y": "2023",
    "isbn": "9785919964636",
    "c": "https://i.postimg.cc/YC75Fzwb/006.jpg",
    "pub": "XL Media",
    "g": [
      "Сэйнэн",
      "Экшен",
      "Приключения",
      "Драма",
      "Фэнтези",
      "Ужасы"
    ],
    "tv": 0,
    "oneshot": false
  },
  {
    "id": 1778263334907,
    "t": "Берсерк",
    "series": "Берсерк",
    "a": [
      "Кэнтаро Миура"
    ],
    "v": 7,
    "p": 482,
    "y": "2024",
    "isbn": "9785919965008",
    "c": "https://i.postimg.cc/MK1kXrgw/007.jpg",
    "pub": "XL Media",
    "g": [
      "Сэйнэн",
      "Экшен",
      "Приключения",
      "Драма",
      "Фэнтези",
      "Ужасы"
    ],
    "tv": 0,
    "oneshot": false
  },
  {
    "id": 1778264253516,
    "t": "Берсерк",
    "series": "Берсерк",
    "a": [
      "Кэнтаро Миура"
    ],
    "v": 8,
    "p": 474,
    "y": "2024",
    "isbn": "9785919965015",
    "c": "https://i.postimg.cc/Sx4B9fhF/008.jpg",
    "pub": "XL Media",
    "g": [
      "Сэйнэн",
      "Экшен",
      "Приключения",
      "Драма",
      "Фэнтези",
      "Ужасы"
    ],
    "tv": 0,
    "oneshot": false
  },
  {
    "id": 1778264356249,
    "t": "Берсерк",
    "series": "Берсерк",
    "a": [
      "Кэнтаро Миура"
    ],
    "v": 9,
    "p": 474,
    "y": "2024",
    "isbn": "9785919965114",
    "c": "https://i.postimg.cc/zfBPwd27/009.jpg",
    "pub": "XL Media",
    "g": [
      "Сэйнэн",
      "Экшен",
      "Приключения",
      "Драма",
      "Фэнтези",
      "Ужасы"
    ],
    "tv": 0,
    "oneshot": false
  },
  {
    "id": 1778264462212,
    "t": "Берсерк",
    "series": "Берсерк",
    "a": [
      "Кэнтаро Миура"
    ],
    "v": 10,
    "p": 466,
    "y": "2025",
    "isbn": "9785919965220",
    "c": "https://i.postimg.cc/N0MP8NCR/010.jpg",
    "pub": "XL Media",
    "g": [
      "Сэйнэн",
      "Экшен",
      "Приключения",
      "Драма",
      "Фэнтези",
      "Ужасы"
    ],
    "tv": 0,
    "oneshot": false
  },
  {
    "id": 1778271763528,
    "t": "Берсерк",
    "series": "Берсерк",
    "a": [
      "Кэнтаро Миура"
    ],
    "v": 11,
    "p": 466,
    "y": "2025",
    "isbn": "9785919965411",
    "c": "https://i.postimg.cc/LsbQxzGD/011.jpg",
    "pub": "XL Media",
    "g": [
      "Сэйнэн",
      "Экшен",
      "Приключения",
      "Драма",
      "Фэнтези",
      "Ужасы"
    ],
    "tv": 0,
    "oneshot": false
  },
  {
    "id": 1778271869262,
    "t": "Берсерк",
    "series": "Берсерк",
    "a": [
      "Кэнтаро Миура"
    ],
    "v": 12,
    "p": 416,
    "y": "2025",
    "isbn": "9785919965466",
    "c": "https://i.postimg.cc/Gp5gXk6Q/012.jpg",
    "pub": "XL Media",
    "g": [
      "Сэйнэн",
      "Экшен",
      "Приключения",
      "Драма",
      "Фэнтези",
      "Ужасы"
    ],
    "tv": 0,
    "oneshot": false
  },
  {
    "id": 1778271938898,
    "t": "Берсерк",
    "series": "Берсерк",
    "a": [
      "Кэнтаро Миура"
    ],
    "v": 13,
    "p": 448,
    "y": "2026",
    "isbn": "9785919965633",
    "c": "https://i.postimg.cc/ncGdy864/013.jpg",
    "pub": "XL Media",
    "g": [
      "Сэйнэн",
      "Экшен",
      "Приключения",
      "Драма",
      "Фэнтези",
      "Ужасы"
    ],
    "tv": 0,
    "oneshot": false
  },
  {
    "id": 1778272015677,
    "t": "Берсерк",
    "series": "Берсерк",
    "a": [
      "Кэнтаро Миура"
    ],
    "v": 14,
    "p": 450,
    "y": "2026",
    "isbn": "9785919965640",
    "c": "https://i.postimg.cc/DyPC9VtP/014.jpg",
    "pub": "XL Media",
    "g": [
      "Сэйнэн",
      "Экшен",
      "Приключения",
      "Драма",
      "Фэнтези",
      "Ужасы"
    ],
    "tv": 0,
    "oneshot": false
  },
  {
    "id": 1778272080953,
    "t": "Берсерк",
    "series": "Берсерк",
    "a": [
      "Кэнтаро Миура"
    ],
    "v": 15,
    "p": 450,
    "y": "2026",
    "isbn": "9785919965657",
    "c": "https://i.postimg.cc/rFMjCnKz/015.jpg",
    "pub": "XL Media",
    "g": [
      "Сэйнэн",
      "Экшен",
      "Приключения",
      "Драма",
      "Фэнтези",
      "Ужасы"
    ],
    "tv": 0,
    "oneshot": false
  },
  {
    "id": 1778574374742,
    "t": "Ателье колдовских колпаков",
    "series": "Ателье колдовских колпаков",
    "a": [
      "Камомэ Сирахама"
    ],
    "v": 1,
    "p": 208,
    "y": "2020",
    "isbn": "9785604344309",
    "c": "https://i.postimg.cc/jjnnMjWG/001.jpg",
    "pub": "Истари Комикс",
    "g": [
      "Сэйнэн",
      "Фэнтези"
    ],
    "tv": 0,
    "oneshot": false
  },
  {
    "id": 1778574433914,
    "t": "Ателье колдовских колпаков",
    "series": "Ателье колдовских колпаков",
    "a": [
      "Камомэ Сирахама"
    ],
    "v": 2,
    "p": 192,
    "y": "2020",
    "isbn": "9785604344316",
    "c": "https://i.postimg.cc/N022d09h/002.jpg",
    "pub": "Истари Комикс",
    "g": [
      "Сэйнэн",
      "Фэнтези"
    ],
    "tv": 0,
    "oneshot": false
  },
  {
    "id": 1778574492108,
    "t": "Ателье колдовских колпаков",
    "series": "Ателье колдовских колпаков",
    "a": [
      "Камомэ Сирахама"
    ],
    "v": 3,
    "p": 192,
    "y": "2021",
    "isbn": "9785604344323",
    "c": "https://i.postimg.cc/hGQQ2GzW/003.jpg",
    "pub": "Истари Комикс",
    "g": [
      "Сэйнэн",
      "Фэнтези"
    ],
    "tv": 0,
    "oneshot": false
  },
  {
    "id": 1778574564998,
    "t": "Ателье колдовских колпаков",
    "series": "Ателье колдовских колпаков",
    "a": [
      "Камомэ Сирахама"
    ],
    "v": 4,
    "p": 192,
    "y": "2021",
    "isbn": "9785604344330",
    "c": "https://i.postimg.cc/Lsggxsq7/004.jpg",
    "pub": "Истари Комикс",
    "g": [
      "Сэйнэн",
      "Фэнтези"
    ],
    "tv": 0,
    "oneshot": false
  },
  {
    "id": 1778574650146,
    "t": "Ателье колдовских колпаков",
    "series": "Ателье колдовских колпаков",
    "a": [
      "Камомэ Сирахама"
    ],
    "v": 5,
    "p": 192,
    "y": "2023",
    "isbn": "9785907539501",
    "c": "https://i.postimg.cc/50cYTMvG/005.jpg",
    "pub": "Истари Комикс",
    "g": [
      "Сэйнэн",
      "Фэнтези"
    ],
    "tv": 0,
    "oneshot": false
  },
  {
    "id": 1778574700686,
    "t": "Ателье колдовских колпаков",
    "series": "Ателье колдовских колпаков",
    "a": [
      "Камомэ Сирахама"
    ],
    "v": 6,
    "p": 192,
    "y": "2024",
    "isbn": "9785907539518",
    "c": "https://i.postimg.cc/MTkMN8Rr/006.jpg",
    "pub": "Истари Комикс",
    "g": [
      "Сэйнэн",
      "Фэнтези"
    ],
    "tv": 0,
    "oneshot": false
  },
  {
    "id": 1778574761402,
    "t": "Ателье колдовских колпаков",
    "series": "Ателье колдовских колпаков",
    "a": [
      "Камомэ Сирахама"
    ],
    "v": 7,
    "p": 176,
    "y": "2024",
    "isbn": "9785907539525",
    "c": "https://i.postimg.cc/858J9VMQ/007.jpg",
    "pub": "Истари Комикс",
    "g": [
      "Сэйнэн",
      "Фэнтези"
    ],
    "tv": 0,
    "oneshot": false
  },
  {
    "id": 1778575425067,
    "t": "Ателье колдовских колпаков",
    "series": "Ателье колдовских колпаков",
    "a": [
      "Камомэ Сирахама"
    ],
    "v": 8,
    "p": 160,
    "y": "2024",
    "isbn": "9785907539532",
    "c": "https://i.postimg.cc/pTNh4tzM/008.jpg",
    "pub": "Истари Комикс",
    "g": [
      "Сэйнэн",
      "Фэнтези"
    ],
    "tv": 0,
    "oneshot": false
  },
  {
    "id": 1778575470217,
    "t": "Ателье колдовских колпаков",
    "series": "Ателье колдовских колпаков",
    "a": [
      "Камомэ Сирахама"
    ],
    "v": 9,
    "p": 176,
    "y": "2025",
    "isbn": "9785907841819",
    "c": "https://i.postimg.cc/26pbMfhf/009.jpg",
    "pub": "Истари Комикс",
    "g": [
      "Сэйнэн",
      "Фэнтези"
    ],
    "tv": 0,
    "oneshot": false
  },
  {
    "id": 1778575510690,
    "t": "Ателье колдовских колпаков",
    "series": "Ателье колдовских колпаков",
    "a": [
      "Камомэ Сирахама"
    ],
    "v": 10,
    "p": 160,
    "y": "2025",
    "isbn": "9785907841826",
    "c": "https://i.postimg.cc/B6WLkGH0/010.jpg",
    "pub": "Истари Комикс",
    "g": [
      "Сэйнэн",
      "Фэнтези"
    ],
    "tv": 0,
    "oneshot": false
  },
  {
    "id": 1778575549674,
    "t": "Ателье колдовских колпаков",
    "series": "Ателье колдовских колпаков",
    "a": [
      "Камомэ Сирахама"
    ],
    "v": 11,
    "p": 160,
    "y": "2025",
    "isbn": "9785907841833",
    "c": "https://i.postimg.cc/V6yrpcnz/011.jpg",
    "pub": "Истари Комикс",
    "g": [
      "Сэйнэн",
      "Фэнтези"
    ],
    "tv": 0,
    "oneshot": false
  },
  {
    "id": 1778575618628,
    "t": "Ателье колдовских колпаков",
    "series": "Ателье колдовских колпаков",
    "a": [
      "Камомэ Сирахама"
    ],
    "v": 12,
    "p": 184,
    "y": "2025",
    "isbn": "9785907841840",
    "c": "https://i.postimg.cc/gJ9XQP8c/012.jpg",
    "pub": "Истари Комикс",
    "g": [
      "Сэйнэн",
      "Фэнтези"
    ],
    "tv": 0,
    "oneshot": false
  },
  {
    "id": 1778575657711,
    "t": "Ателье колдовских колпаков",
    "series": "Ателье колдовских колпаков",
    "a": [
      "Камомэ Сирахама"
    ],
    "v": 13,
    "p": 184,
    "y": "2025",
    "isbn": "9785907922143",
    "c": "https://i.postimg.cc/vBRgkdfZ/013.jpg",
    "pub": "Истари Комикс",
    "g": [
      "Сэйнэн",
      "Фэнтези"
    ],
    "tv": 0,
    "oneshot": false
  },
  {
    "id": 1777400051106,
    "t": "One-Punch Man",
    "series": "One-Punch Man",
    "a": [
      "One",
      "Юскэ Мурата"
    ],
    "v": 1,
    "p": 400,
    "y": "2018",
    "isbn": "9785389141117",
    "c": "https://i.postimg.cc/PrM2snc4/001.jpg",
    "pub": "Азбука",
    "g": [
      "Сэйнэн",
      "Экшен",
      "Комедия"
    ],
    "tv": 0,
    "oneshot": false
  },
  {
    "id": 1777400159873,
    "t": "One-Punch Man",
    "series": "One-Punch Man",
    "a": [
      "One",
      "Юскэ Мурата"
    ],
    "v": 2,
    "p": 416,
    "y": "2018",
    "isbn": "9785389144385",
    "c": "https://i.postimg.cc/zXk0ZYMS/002.jpg",
    "pub": "Азбука",
    "g": [
      "Сэйнэн",
      "Экшен",
      "Комедия"
    ],
    "tv": 0,
    "oneshot": false
  },
  {
    "id": 1777984485881,
    "t": "One-Punch Man",
    "series": "One-Punch Man",
    "a": [
      "One",
      "Юскэ Мурата"
    ],
    "v": 3,
    "p": 416,
    "y": "2018",
    "isbn": "9785389148857",
    "c": "https://i.postimg.cc/qMGjVHYG/003.jpg",
    "pub": "Азбука",
    "g": [
      "Сэйнэн",
      "Экшен",
      "Комедия"
    ],
    "tv": 0,
    "oneshot": false
  },
  {
    "id": 1777984586119,
    "t": "One-Punch Man",
    "series": "One-Punch Man",
    "a": [
      "One",
      "Юскэ Мурата"
    ],
    "v": 4,
    "p": 400,
    "y": "2019",
    "isbn": "9785389155459",
    "c": "https://i.postimg.cc/CLDtt2H1/004.jpg",
    "pub": "Азбука",
    "g": [
      "Сэйнэн",
      "Экшен",
      "Комедия"
    ],
    "tv": 0,
    "oneshot": false
  },
  {
    "id": 1777984677153,
    "t": "One-Punch Man",
    "series": "One-Punch Man",
    "a": [
      "One",
      "Юскэ Мурата"
    ],
    "v": 5,
    "p": 416,
    "y": "2019",
    "isbn": "9785389163232",
    "c": "https://i.postimg.cc/yYTv4C5Q/005.jpg",
    "pub": "Азбука",
    "g": [
      "Сэйнэн",
      "Экшен",
      "Комедия"
    ],
    "tv": 0,
    "oneshot": false
  },
  {
    "id": 1777984772887,
    "t": "One-Punch Man",
    "series": "One-Punch Man",
    "a": [
      "One",
      "Юскэ Мурата"
    ],
    "v": 6,
    "p": 416,
    "y": "2019",
    "isbn": "9785389167698",
    "c": "https://i.postimg.cc/rw4fzRYL/006.jpg",
    "pub": "Азбука",
    "g": [
      "Сэйнэн",
      "Экшен",
      "Комедия"
    ],
    "tv": 0,
    "oneshot": false
  },
  {
    "id": 1777984907227,
    "t": "One-Punch Man",
    "series": "One-Punch Man",
    "a": [
      "One",
      "Юскэ Мурата"
    ],
    "v": 7,
    "p": 416,
    "y": "2019",
    "isbn": "9785389173859",
    "c": "https://i.postimg.cc/9Q9LzwN2/007.jpg",
    "pub": "Азбука",
    "g": [
      "Сэйнэн",
      "Экшен",
      "Комедия"
    ],
    "tv": 0,
    "oneshot": false
  },
  {
    "id": 1777984997960,
    "t": "One-Punch Man",
    "series": "One-Punch Man",
    "a": [
      "One",
      "Юскэ Мурата"
    ],
    "v": 8,
    "p": 416,
    "y": "2020",
    "isbn": "9785389176836",
    "c": "https://i.postimg.cc/sgWT1GHk/008.jpg",
    "pub": "Азбука",
    "g": [
      "Сэйнэн",
      "Экшен",
      "Комедия"
    ],
    "tv": 0,
    "oneshot": false
  },
  {
    "id": 1777985198603,
    "t": "One-Punch Man",
    "series": "One-Punch Man",
    "a": [
      "One",
      "Юскэ Мурата"
    ],
    "v": 9,
    "p": 400,
    "y": "2020",
    "isbn": "9785389176850",
    "c": "https://i.postimg.cc/JzXptHd1/009.jpg",
    "pub": "Азбука",
    "g": [
      "Сэйнэн",
      "Экшен",
      "Комедия"
    ],
    "tv": 0,
    "oneshot": false
  },
  {
    "id": 1777985300998,
    "t": "One-Punch Man",
    "series": "One-Punch Man",
    "a": [
      "One",
      "Юскэ Мурата"
    ],
    "v": 10,
    "p": 424,
    "y": "2024",
    "isbn": "9785389176867",
    "c": "https://i.postimg.cc/kXyf3PZz/010.jpg",
    "pub": "Азбука",
    "g": [
      "Сэйнэн",
      "Экшен",
      "Комедия"
    ],
    "tv": 0,
    "oneshot": false
  },
  {
    "id": 1777985420912,
    "t": "One-Punch Man",
    "series": "One-Punch Man",
    "a": [
      "One",
      "Юскэ Мурата"
    ],
    "v": 11,
    "p": 432,
    "y": "2021",
    "isbn": "9785389199774",
    "c": "https://i.postimg.cc/gksZszX6/011.jpg",
    "pub": "Азбука",
    "g": [
      "Сэйнэн",
      "Экшен",
      "Комедия"
    ],
    "tv": 0,
    "oneshot": false
  },
  {
    "id": 1777985696234,
    "t": "One-Punch Man",
    "series": "One-Punch Man",
    "a": [
      "One",
      "Юскэ Мурата"
    ],
    "v": 12,
    "p": 432,
    "y": "2022",
    "isbn": "9785389214897",
    "c": "https://i.postimg.cc/rw4fzRYt/012.jpg",
    "pub": "Азбука",
    "g": [
      "Сэйнэн",
      "Экшен",
      "Комедия"
    ],
    "tv": 0,
    "oneshot": false
  },
  {
    "id": 1777985867666,
    "t": "One-Punch Man",
    "series": "One-Punch Man",
    "a": [
      "One",
      "Юскэ Мурата"
    ],
    "v": 13,
    "p": 384,
    "y": "2023",
    "isbn": "9785389223288",
    "c": "https://i.postimg.cc/qMP9mTPV/013.jpg",
    "pub": "Азбука",
    "g": [
      "Сэйнэн",
      "Экшен",
      "Комедия"
    ],
    "tv": 0,
    "oneshot": false
  },
  {
    "id": 1777987055046,
    "t": "One-Punch Man",
    "series": "One-Punch Man",
    "a": [
      "One",
      "Юскэ Мурата"
    ],
    "v": 14,
    "p": 400,
    "y": "2023",
    "isbn": "9785389242999",
    "c": "https://i.postimg.cc/nLt0mV6L/014.jpg",
    "pub": "Азбука",
    "g": [
      "Сэйнэн",
      "Экшен",
      "Комедия"
    ],
    "tv": 0,
    "oneshot": false
  },
  {
    "id": 1777987312341,
    "t": "One-Punch Man",
    "series": "One-Punch Man",
    "a": [
      "One",
      "Юскэ Мурата"
    ],
    "v": 15,
    "p": 392,
    "y": "2024",
    "isbn": "9785389272316",
    "c": "https://i.postimg.cc/P5rKdFsS/015.jpg",
    "pub": "Азбука",
    "g": [
      "Сэйнэн",
      "Экшен",
      "Комедия"
    ],
    "tv": 0,
    "oneshot": false
  },
  {
    "id": 1777987416875,
    "t": "One-Punch Man",
    "series": "One-Punch Man",
    "a": [
      "One",
      "Юскэ Мурата"
    ],
    "v": 16,
    "p": 448,
    "y": "2025",
    "isbn": "9785389294202",
    "c": "https://i.postimg.cc/vZHXGSFq/016.jpg",
    "pub": "Азбука",
    "g": [
      "Сэйнэн",
      "Экшен",
      "Комедия"
    ],
    "tv": 0,
    "oneshot": false
  },
  {
    "id": 1777987513630,
    "t": "One-Punch Man",
    "series": "One-Punch Man",
    "a": [
      "One",
      "Юскэ Мурата"
    ],
    "v": 17,
    "p": 432,
    "y": "2026",
    "isbn": "9785389316096",
    "c": "https://i.postimg.cc/nhcTnwbW/017.jpg",
    "pub": "Азбука",
    "g": [
      "Сэйнэн",
      "Экшен",
      "Комедия"
    ],
    "tv": 0,
    "oneshot": false
  },
  {
    "id": "1778082091546",
    "t": "Death Note. Истории",
    "series": "Death Note. Истории",
    "a": [
      "Цугуми Ооба",
      "Такэси Обата"
    ],
    "g": [
      "Сёнен",
      "Сверхъестественное",
      "Триллер"
    ],
    "v": 1,
    "tv": 1,
    "oneshot": true,
    "p": 226,
    "y": "2022",
    "isbn": "9785389201040",
    "pub": "Азбука",
    "c": "https://i.postimg.cc/855vn8SC/00003.jpg"
  },
  {
    "id": 1778081339311,
    "t": "Death Note",
    "series": "Death Note",
    "a": [
      "Цугуми Ооба",
      "Такэси Обата"
    ],
    "v": 1,
    "p": 392,
    "y": "2017",
    "isbn": "9785389137240",
    "c": "https://i.postimg.cc/ZnH1YyQP/001.jpg",
    "pub": "Азбука",
    "g": [
      "Сёнен",
      "Сверхъестественное",
      "Триллер"
    ],
    "tv": 0,
    "oneshot": false
  },
  {
    "id": 1778081395196,
    "t": "Death Note",
    "series": "Death Note",
    "a": [
      "Цугуми Ооба",
      "Такэси Обата"
    ],
    "v": 2,
    "p": 404,
    "y": "2017",
    "isbn": "9785389137189",
    "c": "https://i.postimg.cc/L5Dr4ZW3/002.jpg",
    "pub": "Азбука",
    "g": [
      "Сёнен",
      "Сверхъестественное",
      "Триллер"
    ],
    "tv": 0,
    "oneshot": false
  },
  {
    "id": 1778081527200,
    "t": "Death Note",
    "series": "Death Note",
    "a": [
      "Цугуми Ооба",
      "Такэси Обата"
    ],
    "v": 3,
    "p": 416,
    "y": "2018",
    "isbn": "9785389141544",
    "c": "https://i.postimg.cc/5ygZ9Frq/003.jpg",
    "pub": "Азбука",
    "g": [
      "Сёнен",
      "Сверхъестественное",
      "Триллер"
    ],
    "tv": 0,
    "oneshot": false
  },
  {
    "id": 1778081623779,
    "t": "Death Note",
    "series": "Death Note",
    "a": [
      "Цугуми Ооба",
      "Такэси Обата"
    ],
    "v": 4,
    "p": 420,
    "y": "2018",
    "isbn": "9785389141551",
    "c": "https://i.postimg.cc/8c4qkrYb/004.jpg",
    "pub": "Азбука",
    "g": [
      "Сёнен",
      "Сверхъестественное",
      "Триллер"
    ],
    "tv": 0,
    "oneshot": false
  },
  {
    "id": 1778081836494,
    "t": "Death Note",
    "series": "Death Note",
    "a": [
      "Цугуми Ооба",
      "Такэси Обата"
    ],
    "v": 5,
    "p": 384,
    "y": "2018",
    "isbn": "9785389141568",
    "c": "https://i.postimg.cc/d36zQTfx/005.jpg",
    "pub": "Азбука",
    "g": [
      "Сёнен",
      "Сверхъестественное",
      "Триллер"
    ],
    "tv": 0,
    "oneshot": false
  },
  {
    "id": 1778081901567,
    "t": "Death Note",
    "series": "Death Note",
    "a": [
      "Цугуми Ооба",
      "Такэси Обата"
    ],
    "v": 6,
    "p": 428,
    "y": "2018",
    "isbn": "9785389150041",
    "c": "https://i.postimg.cc/5ygZ9Frs/006.jpg",
    "pub": "Азбука",
    "g": [
      "Сёнен",
      "Сверхъестественное",
      "Триллер"
    ],
    "tv": 0,
    "oneshot": false
  },
  {
    "id": "1778596994077",
    "t": "Старина",
    "series": "Старина",
    "a": [
      "Гарон Цутия",
      "Нобуаки Минэгиси"
    ],
    "g": [
      "Сэйнэн",
      "Экшен",
      "Драма",
      "Тайна"
    ],
    "v": 4,
    "p": 412,
    "y": "2024",
    "isbn": "9785907576292",
    "pub": "Alt Graph",
    "c": "https://i.postimg.cc/gJ1nQDHD/004.jpg",
    "tv": 0,
    "oneshot": false
  },
  {
    "id": "1778597027222",
    "t": "Старина",
    "series": "Старина",
    "a": [
      "Гарон Цутия",
      "Нобуаки Минэгиси"
    ],
    "g": [
      "Сэйнэн",
      "Экшен",
      "Драма",
      "Тайна"
    ],
    "v": 3,
    "p": 420,
    "y": "2024",
    "isbn": "9785907576285",
    "pub": "Alt Graph",
    "c": "https://i.postimg.cc/cJ9KMZK2/003.jpg",
    "tv": 0,
    "oneshot": false
  },
  {
    "id": "1778666881842",
    "t": "Оглянись",
    "series": "Оглянись",
    "a": [
      "Тацуки Фудзимото"
    ],
    "g": [
      "Сёнен",
      "Драма"
    ],
    "v": 1,
    "tv": 1,
    "oneshot": true,
    "p": 144,
    "y": "2024",
    "isbn": "9785389264762",
    "pub": "Азбука",
    "c": "https://i.postimg.cc/LsMyR7jX/00007.jpg"
  },
  {
    "id": "1778666979037",
    "t": "Прощай, Эри",
    "series": "Прощай, Эри",
    "a": [
      "Тацуки Фудзимото"
    ],
    "g": [
      "Сёнен",
      "Драма"
    ],
    "v": 1,
    "tv": 1,
    "oneshot": true,
    "p": 208,
    "y": "2025",
    "isbn": "9785389250192",
    "pub": "Азбука",
    "c": "https://i.postimg.cc/3xGLs70D/00006.jpg"
  },
  {
    "id": "1778667879164",
    "t": "Игра друзей",
    "series": "Игра друзей",
    "a": [
      "Микото Ямагути",
      "Юки Сато"
    ],
    "g": [
      "Сёнен",
      "Триллер"
    ],
    "v": 1,
    "tv": 0,
    "oneshot": false,
    "p": 400,
    "y": "2025",
    "isbn": "9785389283893",
    "pub": "Азбука",
    "c": "https://i.postimg.cc/7PXj9xSZ/001.jpg"
  },
  {
    "id": "1778667944126",
    "t": "Игра друзей",
    "series": "Игра друзей",
    "a": [
      "Микото Ямагути",
      "Юки Сато"
    ],
    "g": [
      "Сёнен",
      "Триллер"
    ],
    "v": 2,
    "tv": 0,
    "oneshot": false,
    "p": 392,
    "y": "2025",
    "isbn": "9785389289062",
    "pub": "Азбука",
    "c": "https://i.postimg.cc/VLVpyD7C/002.jpg"
  },
  {
    "id": "1778667990373",
    "t": "Игра друзей",
    "series": "Игра друзей",
    "a": [
      "Микото Ямагути",
      "Юки Сато"
    ],
    "g": [
      "Сёнен",
      "Триллер"
    ],
    "v": 3,
    "tv": 0,
    "oneshot": false,
    "p": 384,
    "y": "2025",
    "isbn": "9785389304710",
    "pub": "Азбука",
    "c": "https://i.postimg.cc/ZKM2kVfp/003.jpg"
  },
  {
    "id": "1778668024865",
    "t": "Игра друзей",
    "series": "Игра друзей",
    "a": [
      "Микото Ямагути",
      "Юки Сато"
    ],
    "g": [
      "Сёнен",
      "Триллер"
    ],
    "v": 4,
    "tv": 0,
    "oneshot": false,
    "p": 384,
    "y": "2025",
    "isbn": "9785389311008",
    "pub": "Азбука",
    "c": "https://i.postimg.cc/PrR9G26b/004.jpg"
  },
  {
    "id": "1778668065235",
    "t": "Игра друзей",
    "series": "Игра друзей",
    "a": [
      "Микото Ямагути",
      "Юки Сато"
    ],
    "g": [
      "Сёнен",
      "Триллер"
    ],
    "v": 5,
    "tv": 0,
    "oneshot": false,
    "p": 392,
    "y": "2026",
    "isbn": "9785389318489",
    "pub": "Азбука",
    "c": "https://i.postimg.cc/tCMw02rS/005.jpg"
  },
  {
    "id": "1778668685010",
    "t": "Медалистка",
    "series": "Медалистка",
    "a": [
      "Цурумаикада"
    ],
    "g": [
      "Сэйнэн",
      "Драма",
      "Спорт"
    ],
    "v": 1,
    "tv": 0,
    "oneshot": false,
    "p": 224,
    "y": "2023",
    "isbn": "9785389238008",
    "pub": "Азбука",
    "c": "https://i.postimg.cc/J4R8P6ym/001.jpg"
  },
  {
    "id": "1778668743249",
    "t": "Медалистка",
    "series": "Медалистка",
    "a": [
      "Цурумаикада"
    ],
    "g": [
      "Сэйнэн",
      "Драма",
      "Спорт"
    ],
    "v": 2,
    "tv": 0,
    "oneshot": false,
    "p": 192,
    "y": "2023",
    "isbn": "9785389241398",
    "pub": "Азбука",
    "c": "https://i.postimg.cc/Z5RShWFD/002.jpg"
  },
  {
    "id": "1778668797572",
    "t": "Медалистка",
    "series": "Медалистка",
    "a": [
      "Цурумаикада"
    ],
    "g": [
      "Сэйнэн",
      "Драма",
      "Спорт"
    ],
    "v": 3,
    "tv": 0,
    "oneshot": false,
    "p": 192,
    "y": "2024",
    "isbn": "9785389245327",
    "pub": "Азбука",
    "c": "https://i.postimg.cc/K8z2y1rH/003.jpg"
  },
  {
    "id": "1778668837262",
    "t": "Медалистка",
    "series": "Медалистка",
    "a": [
      "Цурумаикада"
    ],
    "g": [
      "Сэйнэн",
      "Драма",
      "Спорт"
    ],
    "v": 4,
    "tv": 0,
    "oneshot": false,
    "p": 192,
    "y": "2024",
    "isbn": "9785389249059",
    "pub": "Азбука",
    "c": "https://i.postimg.cc/Gm2C14J7/004.jpg"
  },
  {
    "id": "1778668876909",
    "t": "Медалистка",
    "series": "Медалистка",
    "a": [
      "Цурумаикада"
    ],
    "g": [
      "Сэйнэн",
      "Драма",
      "Спорт"
    ],
    "v": 5,
    "tv": 0,
    "oneshot": false,
    "p": 176,
    "y": "2024",
    "isbn": "9785389252035",
    "pub": "Азбука",
    "c": "https://i.postimg.cc/Z5MhYJVV/005.jpg"
  },
  {
    "id": "1778668990242",
    "t": "Медалистка",
    "series": "Медалистка",
    "a": [
      "Цурумаикада"
    ],
    "g": [
      "Сэйнэн",
      "Драма",
      "Спорт"
    ],
    "v": 6,
    "tv": 0,
    "oneshot": false,
    "p": 192,
    "y": "2024",
    "isbn": "9785389245327",
    "pub": "Азбука",
    "c": "https://i.postimg.cc/FHBQFhTt/006.jpg"
  },
  {
    "id": "1778669038985",
    "t": "Медалистка",
    "series": "Медалистка",
    "a": [
      "Цурумаикада"
    ],
    "g": [
      "Сэйнэн",
      "Драма",
      "Спорт"
    ],
    "v": 7,
    "tv": 0,
    "oneshot": false,
    "p": 192,
    "y": "2025",
    "isbn": "9785389270718",
    "pub": "Азбука",
    "c": "https://i.postimg.cc/3w0Qdzq3/007.jpg"
  },
  {
    "id": "1778669099482",
    "t": "Медалистка",
    "series": "Медалистка",
    "a": [
      "Цурумаикада"
    ],
    "g": [
      "Сэйнэн",
      "Драма",
      "Спорт"
    ],
    "v": 8,
    "tv": 0,
    "oneshot": false,
    "p": 176,
    "y": "2025",
    "isbn": "9785389277502",
    "pub": "Азбука",
    "c": "https://i.postimg.cc/25LNVgt6/008.jpg"
  },
  {
    "id": "1778669262285",
    "t": "Медалистка",
    "series": "Медалистка",
    "a": [
      "Цурумаикада"
    ],
    "g": [
      "Сэйнэн",
      "Драма",
      "Спорт"
    ],
    "v": 9,
    "tv": 0,
    "oneshot": false,
    "p": 192,
    "y": "2025",
    "isbn": "9785389277519",
    "pub": "Азбука",
    "c": "https://i.postimg.cc/nL9fCNW4/009.jpg"
  },
  {
    "id": "1778669291485",
    "t": "Медалистка",
    "series": "Медалистка",
    "a": [
      "Цурумаикада"
    ],
    "g": [
      "Сэйнэн",
      "Драма",
      "Спорт"
    ],
    "v": 10,
    "tv": 0,
    "oneshot": false,
    "p": 192,
    "y": "2026",
    "isbn": "9785389309623",
    "pub": "Азбука",
    "c": "https://i.postimg.cc/cHqyYXq3/010.jpg"
  },
  {
    "id": "1778669324500",
    "t": "Медалистка",
    "series": "Медалистка",
    "a": [
      "Цурумаикада"
    ],
    "g": [
      "Сэйнэн",
      "Драма",
      "Спорт"
    ],
    "v": 11,
    "tv": 0,
    "oneshot": false,
    "p": 192,
    "y": "2026",
    "isbn": "9785389309630",
    "pub": "Азбука",
    "c": "https://i.postimg.cc/C1yTDmyv/011.jpg"
  },
  {
    "id": "1778760413833",
    "t": "Блуждающий остров",
    "series": "Блуждающий остров",
    "a": [
      "Кэндзи Цурута"
    ],
    "g": [
      "Сэйнэн",
      "Тайна"
    ],
    "v": 1,
    "tv": 0,
    "oneshot": false,
    "p": 192,
    "y": "2022",
    "isbn": "9785907576032",
    "pub": "Alt Graph",
    "c": "https://i.postimg.cc/1tj2qgBG/001.jpg"
  },
  {
    "id": "1778760493799",
    "t": "Блуждающий остров",
    "series": "Блуждающий остров",
    "a": [
      "Кэндзи Цурута"
    ],
    "g": [
      "Сэйнэн",
      "Тайна"
    ],
    "v": 2,
    "tv": 0,
    "oneshot": false,
    "p": 192,
    "y": "2022",
    "isbn": "9785907576049",
    "pub": "Alt Graph",
    "c": "https://i.postimg.cc/hjjNv8Lh/002.jpg"
  },
  {
    "id": "1778849788986",
    "t": "Босоногий Гэн",
    "series": "Босоногий Гэн",
    "a": [
      "Кэйдзи Накадзава"
    ],
    "g": [
      "Сёнен",
      "Драма"
    ],
    "v": 1,
    "tv": 0,
    "oneshot": false,
    "p": 896,
    "y": "2021",
    "isbn": "9785905295799",
    "pub": "Alt Graph",
    "c": "https://i.postimg.cc/gJPm0Ydp/001.jpg"
  },
  {
    "id": "1778849860167",
    "t": "Босоногий Гэн",
    "series": "Босоногий Гэн",
    "a": [
      "Кэйдзи Накадзава"
    ],
    "g": [
      "Сёнен",
      "Драма"
    ],
    "v": 2,
    "tv": 0,
    "oneshot": false,
    "p": 880,
    "y": "2021",
    "isbn": "9785905295805",
    "pub": "Alt Graph",
    "c": "https://i.postimg.cc/SspkKyqm/002.jpg"
  },
  {
    "id": "1778849922114",
    "t": "Босоногий Гэн",
    "series": "Босоногий Гэн",
    "a": [
      "Кэйдзи Накадзава"
    ],
    "g": [
      "Сёнен",
      "Драма"
    ],
    "v": 3,
    "tv": 0,
    "oneshot": false,
    "p": 864,
    "y": "2021",
    "isbn": "9785905295812",
    "pub": "Alt Graph",
    "c": "https://i.postimg.cc/TwXfPRG6/003.jpg"
  }
]